sparksrepeater/__init__.py
sparksrepeater/setup.py
sparksrepeater/sparksrepeater.py
sparksrepeater-0.0.1.dist-info/METADATA
sparksrepeater-0.0.1.dist-info/WHEEL
sparksrepeater-0.0.1.dist-info/top_level.txt
sparksrepeater-0.0.1.dist-info/RECORD
